surforama/__init__.py
surforama/_cli.py
surforama/_version.py
surforama/app.py
surforama/constants.py
surforama/napari.yaml
surforama/_tests/__init__.py
surforama/_tests/test_geometry.py
surforama/_tests/test_widget.py
surforama/data/__init__.py
surforama/data/_datasets.py
surforama/gui/__init__.py
surforama/gui/qt_mesh_generator.py
surforama/gui/qt_point_io.py
surforama/gui/qt_surface_picker.py
surforama/io/__init__.py
surforama/io/_reader_plugin.py
surforama/io/mesh.py
surforama/io/star.py
surforama/io/_tests/__init__.py
surforama/io/_tests/test_star.py
surforama/utils/__init__.py
surforama/utils/geometry.py
surforama/utils/napari.py
surforama/utils/stats.py
surforama-0.0.9.dist-info/LICENSE
surforama-0.0.9.dist-info/METADATA
surforama-0.0.9.dist-info/WHEEL
surforama-0.0.9.dist-info/entry_points.txt
surforama-0.0.9.dist-info/top_level.txt
surforama-0.0.9.dist-info/RECORD
