Metadata-Version: 2.1
Name: surforama
Version: 0.0.9
Summary: a tool for using surfaces to explore volumetric data in napari
Home-page: https://github.com/cellcanvas/surforama
Author: Kyle Harrington
Author-email: surforama@kyleharrington.com
License: MIT
Project-URL: Bug Tracker, https://github.com/cellcanvas/surforama/issues
Project-URL: Documentation, https://github.com/cellcanvas/surforama#README.md
Project-URL: Source Code, https://github.com/cellcanvas/surforama
Project-URL: User Support, https://github.com/cellcanvas/surforama/issues
Classifier: Development Status :: 2 - Pre-Alpha
Classifier: Framework :: napari
Classifier: Intended Audience :: Developers
Classifier: License :: OSI Approved :: MIT License
Classifier: Operating System :: OS Independent
Classifier: Programming Language :: Python
Classifier: Programming Language :: Python :: 3
Classifier: Programming Language :: Python :: 3 :: Only
Classifier: Programming Language :: Python :: 3.8
Classifier: Programming Language :: Python :: 3.9
Classifier: Programming Language :: Python :: 3.10
Classifier: Topic :: Scientific/Engineering :: Image Processing
Requires-Python: >=3.8
License-File: LICENSE
Requires-Dist: magicgui
Requires-Dist: mrcfile
Requires-Dist: numpy
Requires-Dist: pooch
Requires-Dist: qtpy
Requires-Dist: pyacvd
Requires-Dist: pyvista
Requires-Dist: rich
Requires-Dist: scikit-image
Requires-Dist: starfile
Requires-Dist: trimesh
Requires-Dist: typer
Provides-Extra: dev
Requires-Dist: napari ; extra == 'dev'
Requires-Dist: pyqt5 ; extra == 'dev'
Requires-Dist: pytest ; extra == 'dev'
Requires-Dist: pytest-cov ; extra == 'dev'
Requires-Dist: pytest-qt ; extra == 'dev'
Requires-Dist: tox ; extra == 'dev'
Requires-Dist: pre-commit ; extra == 'dev'
Provides-Extra: napari
Requires-Dist: napari[all] ; extra == 'napari'
Provides-Extra: testing
Requires-Dist: napari ; extra == 'testing'
Requires-Dist: pyqt5 ; extra == 'testing'
Requires-Dist: pytest ; extra == 'testing'
Requires-Dist: pytest-cov ; extra == 'testing'
Requires-Dist: pytest-qt ; extra == 'testing'
Requires-Dist: tox ; extra == 'testing'
